README.md
setup.py
cheesefactory_email/__init__.py
cheesefactory_email/log.py
cheesefactory_email.egg-info/PKG-INFO
cheesefactory_email.egg-info/SOURCES.txt
cheesefactory_email.egg-info/dependency_links.txt
cheesefactory_email.egg-info/top_level.txt